{
  "agent_case": "high",
  "agent_count": 20,
  "agent_density": 0.204082,
  "base_sweep_name": "sweep_r70_w140_h15_a20_s01",
  "cause_case_name": "cause_03_head_on_traffic",
  "cause_number": "03",
  "corridor_case": "long",
  "debug_suite": "cause_sweep_matrix",
  "description": "Cause matrix 03: opposite_direction_head_on_traffic tested on tunnel ratio 70% with 20 agents.",
  "duplicate_goal_limit": 0,
  "force_shared_store_depot": 0,
  "grid_height": 15,
  "grid_width": 140,
  "hypothesis": "Longer corridors should increase abstraction repair length; more agents per corridor node should increase waits and conflict handling.",
  "left_station": 1000,
  "map_edges": 1326,
  "map_vertices": 504,
  "name": "matrix_c03_r70_w140_h15_a20_s01",
  "pods": 196,
  "right_station": 1099,
  "target_failure_cause": "opposite_direction_head_on_traffic",
  "target_failure_hypothesis": "Opposite-direction traffic creates swap and vertex conflicts inside the tunnel.",
  "tunnel_end_col": 118,
  "tunnel_length": 98,
  "tunnel_row": 7,
  "tunnel_start_col": 21,
  "tunnel_target_ratio": 0.7,
  "tunnel_width_ratio": 0.7
}