{
  "agent_case": "high",
  "agent_count": 20,
  "agent_density": 0.285714,
  "base_sweep_name": "",
  "cause_case_name": "",
  "cause_number": "",
  "corridor_case": "long",
  "debug_suite": "",
  "description": "Cause 03: agents start from both sides and meet head-on.",
  "duplicate_goal_limit": 0,
  "expected_missing_abstraction": false,
  "expected_outcome": "",
  "force_shared_store_depot": 0,
  "graph_mutation": "",
  "grid_height": 17,
  "grid_width": 100,
  "hypothesis": "Longer corridors should increase abstraction repair length; more agents per corridor node should increase waits and conflict handling.",
  "left_station": 814,
  "map_edges": 942,
  "map_vertices": 360,
  "name": "cause_03_head_on_traffic",
  "pods": 140,
  "proof_role": "",
  "right_station": 885,
  "target_failure_cause": "opposite_direction_head_on_traffic",
  "target_failure_hypothesis": "Opposite-direction traffic creates swap and vertex conflicts inside the tunnel.",
  "tunnel_end_col": 84,
  "tunnel_gap_col": "",
  "tunnel_length": 70,
  "tunnel_row": 8,
  "tunnel_start_col": 15,
  "tunnel_target_ratio": 0.7,
  "tunnel_width_ratio": 0.7
}